readme_generator/__init__.py
readme_generator/cli.py
readme_generator/generator.py
readme_generator/templates.py
readme_generator/utils.py
readme_generator/templates/fancy.md.j2
readme_generator/templates/minimal.md.j2
readme_generator/templates/standard.md.j2
sample_project/sample_project/__init__.py
sample_project/sample_project/cli.py
sample_project/tests/test_cli.py
tests/test_cli_workflow.py
tests/test_error_handling.py
tests/test_generator.py
tests/test_template_rendering.py
readmegen_oss-0.1.2.dist-info/METADATA
readmegen_oss-0.1.2.dist-info/WHEEL
readmegen_oss-0.1.2.dist-info/entry_points.txt
readmegen_oss-0.1.2.dist-info/top_level.txt
readmegen_oss-0.1.2.dist-info/RECORD
