Metadata-Version: 2.4
Name: readmegen-oss
Version: 0.1.2
Summary: AI-Powered GitHub README Generator - Zero-friction CLI for professional README files
Author-email: Your Name <your.email@example.com>
License: MIT
Project-URL: Homepage, https://github.com/your-username/ReadmeGen
Project-URL: Documentation, https://github.com/your-username/ReadmeGen#readme
Project-URL: Repository, https://github.com/your-username/ReadmeGen
Project-URL: Issues, https://github.com/your-username/ReadmeGen/issues
Project-URL: Changelog, https://github.com/your-username/ReadmeGen/releases
Keywords: readme,generator,cli,markdown,documentation
Classifier: Development Status :: 4 - Beta
Classifier: Intended Audience :: Developers
Classifier: License :: OSI Approved :: MIT License
Classifier: Operating System :: OS Independent
Classifier: Programming Language :: Python :: 3
Classifier: Programming Language :: Python :: 3.11
Classifier: Programming Language :: Python :: 3.12
Classifier: Programming Language :: Python :: 3.13
Classifier: Topic :: Documentation
Classifier: Topic :: Software Development :: Documentation
Classifier: Topic :: Text Processing :: Markup :: Markdown
Requires-Python: >=3.11
Requires-Dist: typer[all]>=0.9.0
Requires-Dist: jinja2>=3.1.0
Requires-Dist: pyyaml>=6.0
Requires-Dist: rich>=13.0.0
Requires-Dist: questionary>=2.0.0
Provides-Extra: dev
Requires-Dist: pytest>=7.0.0; extra == "dev"
Requires-Dist: pytest-cov>=4.0.0; extra == "dev"
Requires-Dist: black>=23.0.0; extra == "dev"
Requires-Dist: ruff>=0.1.0; extra == "dev"
Requires-Dist: questionary>=2.0.0; extra == "dev"
Provides-Extra: ai
Requires-Dist: openai>=1.0.0; extra == "ai"
Requires-Dist: python-dotenv>=1.0.0; extra == "ai"
Provides-Extra: github
Requires-Dist: PyGithub>=1.59.0; extra == "github"
